{
  "prediction": {
    "match": "Team Heretics vs Team Vitality",
    "date": "2025-04-21 11:52:44",
    "predicted_winner": "Team Vitality",
    "team1_win_probability": 0.19957976043224335,
    "team2_win_probability": 0.8004202395677567,
    "confidence": 0.8004202395677567
  },
  "team_stats": {
    "Team Heretics": {
      "wins": 126,
      "losses": 69,
      "win_rate": 0.6461538461538462,
      "total_score": 246,
      "total_opponent_score": 145,
      "avg_score": 1.2615384615384615,
      "avg_opponent_score": 0.7435897435897436,
      "score_differential": 0.5179487179487179,
      "recent_form": 0.8,
      "opponent_stats": {
        "Natus Vincere": {
          "wins": 4,
          "total_score": 9,
          "total_opponent_score": 2,
          "win_rate": 0.8,
          "avg_score": 1.8,
          "avg_opponent_score": 0.4,
          "score_differential": 1.4
        },
        "Team Vitality": {
          "wins": 1,
          "total_score": 5,
          "total_opponent_score": 15,
          "win_rate": 0.125,
          "avg_score": 0.625,
          "avg_opponent_score": 1.875,
          "score_differential": -1.25
        },
        "GIANTX": {
          "wins": 2,
          "total_score": 4,
          "total_opponent_score": 2,
          "win_rate": 1.0,
          "avg_score": 2.0,
          "avg_opponent_score": 1.0,
          "score_differential": 1.0
        },
        "Apeks": {
          "wins": 1,
          "total_score": 2,
          "total_opponent_score": 1,
          "win_rate": 1.0,
          "avg_score": 2.0,
          "avg_opponent_score": 1.0,
          "score_differential": 1.0
        },
        "Team Liquid": {
          "wins": 2,
          "total_score": 4,
          "total_opponent_score": 8,
          "win_rate": 0.4,
          "avg_score": 0.8,
          "avg_opponent_score": 1.6,
          "score_differential": -0.8
        },
        "BBL Esports": {
          "wins": 1,
          "total_score": 3,
          "total_opponent_score": 4,
          "win_rate": 0.3333333333333333,
          "avg_score": 1.0,
          "avg_opponent_score": 1.3333333333333333,
          "score_differential": -0.33333333333333326
        },
        "Gentle Mates": {
          "wins": 2,
          "total_score": 4,
          "total_opponent_score": 4,
          "win_rate": 0.6666666666666666,
          "avg_score": 1.3333333333333333,
          "avg_opponent_score": 1.3333333333333333,
          "score_differential": 0.0
        },
        "Cloud9": {
          "wins": 0,
          "total_score": 0,
          "total_opponent_score": 1,
          "win_rate": 0.0,
          "avg_score": 0.0,
          "avg_opponent_score": 1.0,
          "score_differential": -1.0
        },
        "FOKUS": {
          "wins": 1,
          "total_score": 1,
          "total_opponent_score": 1,
          "win_rate": 0.5,
          "avg_score": 0.5,
          "avg_opponent_score": 0.5,
          "score_differential": 0.0
        },
        "EDward Gaming": {
          "wins": 1,
          "total_score": 4,
          "total_opponent_score": 3,
          "win_rate": 0.5,
          "avg_score": 2.0,
          "avg_opponent_score": 1.5,
          "score_differential": 0.5
        },
        "LEVIAT\u00c1N": {
          "wins": 1,
          "total_score": 3,
          "total_opponent_score": 3,
          "win_rate": 0.5,
          "avg_score": 1.5,
          "avg_opponent_score": 1.5,
          "score_differential": 0.0
        },
        "Sentinels": {
          "wins": 1,
          "total_score": 3,
          "total_opponent_score": 3,
          "win_rate": 0.5,
          "avg_score": 1.5,
          "avg_opponent_score": 1.5,
          "score_differential": 0.0
        },
        "DRX": {
          "wins": 1,
          "total_score": 2,
          "total_opponent_score": 1,
          "win_rate": 1.0,
          "avg_score": 2.0,
          "avg_opponent_score": 1.0,
          "score_differential": 1.0
        },
        "FNATIC": {
          "wins": 3,
          "total_score": 8,
          "total_opponent_score": 5,
          "win_rate": 0.6,
          "avg_score": 1.6,
          "avg_opponent_score": 1.0,
          "score_differential": 0.6000000000000001
        },
        "Gen.G": {
          "wins": 1,
          "total_score": 4,
          "total_opponent_score": 4,
          "win_rate": 0.5,
          "avg_score": 2.0,
          "avg_opponent_score": 2.0,
          "score_differential": 0.0
        },
        "FunPlus Phoenix": {
          "wins": 2,
          "total_score": 4,
          "total_opponent_score": 2,
          "win_rate": 1.0,
          "avg_score": 2.0,
          "avg_opponent_score": 1.0,
          "score_differential": 1.0
        },
        "FUT Esports": {
          "wins": 6,
          "total_score": 12,
          "total_opponent_score": 3,
          "win_rate": 0.75,
          "avg_score": 1.5,
          "avg_opponent_score": 0.375,
          "score_differential": 1.125
        },
        "KOI": {
          "wins": 4,
          "total_score": 9,
          "total_opponent_score": 8,
          "win_rate": 0.5,
          "avg_score": 1.125,
          "avg_opponent_score": 1.0,
          "score_differential": 0.125
        },
        "G2 Esports": {
          "wins": 2,
          "total_score": 7,
          "total_opponent_score": 7,
          "win_rate": 0.4,
          "avg_score": 1.4,
          "avg_opponent_score": 1.4,
          "score_differential": 0.0
        },
        "100 Thieves": {
          "wins": 1,
          "total_score": 3,
          "total_opponent_score": 2,
          "win_rate": 0.5,
          "avg_score": 1.5,
          "avg_opponent_score": 1.0,
          "score_differential": 0.5
        },
        "Dragon Ranger Gaming": {
          "wins": 1,
          "total_score": 2,
          "total_opponent_score": 0,
          "win_rate": 1.0,
          "avg_score": 2.0,
          "avg_opponent_score": 0.0,
          "score_differential": 2.0
        },
        "Karmine Corp": {
          "wins": 3,
          "total_score": 7,
          "total_opponent_score": 5,
          "win_rate": 0.6,
          "avg_score": 1.4,
          "avg_opponent_score": 1.0,
          "score_differential": 0.3999999999999999
        },
        "Paper Rex": {
          "wins": 0,
          "total_score": 2,
          "total_opponent_score": 5,
          "win_rate": 0.0,
          "avg_score": 1.0,
          "avg_opponent_score": 2.5,
          "score_differential": -1.5
        },
        "UCAM Esports Club": {
          "wins": 2,
          "total_score": 5,
          "total_opponent_score": 6,
          "win_rate": 0.4,
          "avg_score": 1.0,
          "avg_opponent_score": 1.2,
          "score_differential": -0.19999999999999996
        },
        "G2 Gozen": {
          "wins": 1,
          "total_score": 1,
          "total_opponent_score": 0,
          "win_rate": 1.0,
          "avg_score": 1.0,
          "avg_opponent_score": 0.0,
          "score_differential": 1.0
        },
        "Giants Gaming": {
          "wins": 2,
          "total_score": 3,
          "total_opponent_score": 2,
          "win_rate": 0.5,
          "avg_score": 0.75,
          "avg_opponent_score": 0.5,
          "score_differential": 0.25
        },
        "Evil Geniuses": {
          "wins": 0,
          "total_score": 0,
          "total_opponent_score": 2,
          "win_rate": 0.0,
          "avg_score": 0.0,
          "avg_opponent_score": 2.0,
          "score_differential": -2.0
        },
        "BLEED": {
          "wins": 1,
          "total_score": 2,
          "total_opponent_score": 0,
          "win_rate": 1.0,
          "avg_score": 2.0,
          "avg_opponent_score": 0.0,
          "score_differential": 2.0
        },
        "Team Secret": {
          "wins": 0,
          "total_score": 0,
          "total_opponent_score": 1,
          "win_rate": 0.0,
          "avg_score": 0.0,
          "avg_opponent_score": 1.0,
          "score_differential": -1.0
        },
        "Enigma Gaming": {
          "wins": 1,
          "total_score": 1,
          "total_opponent_score": 0,
          "win_rate": 1.0,
          "avg_score": 1.0,
          "avg_opponent_score": 0.0,
          "score_differential": 1.0
        },
        "Rex Regum Qeon": {
          "wins": 1,
          "total_score": 1,
          "total_opponent_score": 0,
          "win_rate": 1.0,
          "avg_score": 1.0,
          "avg_opponent_score": 0.0,
          "score_differential": 1.0
        },
        "Rebels Gaming": {
          "wins": 2,
          "total_score": 4,
          "total_opponent_score": 3,
          "win_rate": 0.4,
          "avg_score": 0.8,
          "avg_opponent_score": 0.6,
          "score_differential": 0.20000000000000007
        },
        "KPI Gaming": {
          "wins": 1,
          "total_score": 3,
          "total_opponent_score": 2,
          "win_rate": 1.0,
          "avg_score": 3.0,
          "avg_opponent_score": 2.0,
          "score_differential": 1.0
        },
        "trashcan": {
          "wins": 1,
          "total_score": 1,
          "total_opponent_score": 0,
          "win_rate": 1.0,
          "avg_score": 1.0,
          "avg_opponent_score": 0.0,
          "score_differential": 1.0
        },
        "BIG": {
          "wins": 2,
          "total_score": 2,
          "total_opponent_score": 0,
          "win_rate": 1.0,
          "avg_score": 1.0,
          "avg_opponent_score": 0.0,
          "score_differential": 1.0
        },
        "GTZ Esports": {
          "wins": 1,
          "total_score": 1,
          "total_opponent_score": 0,
          "win_rate": 1.0,
          "avg_score": 1.0,
          "avg_opponent_score": 0.0,
          "score_differential": 1.0
        },
        "kokpiT": {
          "wins": 1,
          "total_score": 1,
          "total_opponent_score": 0,
          "win_rate": 1.0,
          "avg_score": 1.0,
          "avg_opponent_score": 0.0,
          "score_differential": 1.0
        },
        "Riddle Esports": {
          "wins": 1,
          "total_score": 1,
          "total_opponent_score": 0,
          "win_rate": 1.0,
          "avg_score": 1.0,
          "avg_opponent_score": 0.0,
          "score_differential": 1.0
        },
        "Rapid Ninjas": {
          "wins": 0,
          "total_score": 0,
          "total_opponent_score": 1,
          "win_rate": 0.0,
          "avg_score": 0.0,
          "avg_opponent_score": 1.0,
          "score_differential": -1.0
        },
        "Case Esports": {
          "wins": 1,
          "total_score": 1,
          "total_opponent_score": 3,
          "win_rate": 0.25,
          "avg_score": 0.25,
          "avg_opponent_score": 0.75,
          "score_differential": -0.5
        },
        "4Real": {
          "wins": 1,
          "total_score": 1,
          "total_opponent_score": 0,
          "win_rate": 1.0,
          "avg_score": 1.0,
          "avg_opponent_score": 0.0,
          "score_differential": 1.0
        },
        "Real Betis": {
          "wins": 1,
          "total_score": 1,
          "total_opponent_score": 1,
          "win_rate": 0.5,
          "avg_score": 0.5,
          "avg_opponent_score": 0.5,
          "score_differential": 0.0
        },
        "Arctic": {
          "wins": 1,
          "total_score": 1,
          "total_opponent_score": 3,
          "win_rate": 0.25,
          "avg_score": 0.25,
          "avg_opponent_score": 0.75,
          "score_differential": -0.5
        },
        "Movistar Riders": {
          "wins": 6,
          "total_score": 8,
          "total_opponent_score": 1,
          "win_rate": 0.8571428571428571,
          "avg_score": 1.1428571428571428,
          "avg_opponent_score": 0.14285714285714285,
          "score_differential": 1.0
        },
        "Team Queso": {
          "wins": 0,
          "total_score": 0,
          "total_opponent_score": 3,
          "win_rate": 0.0,
          "avg_score": 0.0,
          "avg_opponent_score": 1.0,
          "score_differential": -1.0
        },
        "BISONS ECLUB": {
          "wins": 0,
          "total_score": 0,
          "total_opponent_score": 1,
          "win_rate": 0.0,
          "avg_score": 0.0,
          "avg_opponent_score": 1.0,
          "score_differential": -1.0
        },
        "EXCEL": {
          "wins": 0,
          "total_score": 0,
          "total_opponent_score": 2,
          "win_rate": 0.0,
          "avg_score": 0.0,
          "avg_opponent_score": 2.0,
          "score_differential": -2.0
        },
        "Camioneros Valorant Club": {
          "wins": 1,
          "total_score": 2,
          "total_opponent_score": 0,
          "win_rate": 1.0,
          "avg_score": 2.0,
          "avg_opponent_score": 0.0,
          "score_differential": 2.0
        },
        "KVM Esports": {
          "wins": 1,
          "total_score": 2,
          "total_opponent_score": 1,
          "win_rate": 1.0,
          "avg_score": 2.0,
          "avg_opponent_score": 1.0,
          "score_differential": 1.0
        },
        "Valar Morghulis": {
          "wins": 0,
          "total_score": 1,
          "total_opponent_score": 2,
          "win_rate": 0.0,
          "avg_score": 1.0,
          "avg_opponent_score": 2.0,
          "score_differential": -1.0
        },
        "Raftel": {
          "wins": 1,
          "total_score": 2,
          "total_opponent_score": 0,
          "win_rate": 1.0,
          "avg_score": 2.0,
          "avg_opponent_score": 0.0,
          "score_differential": 2.0
        },
        "TENSTAR": {
          "wins": 0,
          "total_score": 0,
          "total_opponent_score": 2,
          "win_rate": 0.0,
          "avg_score": 0.0,
          "avg_opponent_score": 2.0,
          "score_differential": -2.0
        },
        "Finest": {
          "wins": 3,
          "total_score": 5,
          "total_opponent_score": 1,
          "win_rate": 1.0,
          "avg_score": 1.6666666666666667,
          "avg_opponent_score": 0.3333333333333333,
          "score_differential": 1.3333333333333335
        },
        "Ninjas in Pyjamas": {
          "wins": 2,
          "total_score": 4,
          "total_opponent_score": 3,
          "win_rate": 0.6666666666666666,
          "avg_score": 1.3333333333333333,
          "avg_opponent_score": 1.0,
          "score_differential": 0.33333333333333326
        },
        "bref": {
          "wins": 1,
          "total_score": 2,
          "total_opponent_score": 1,
          "win_rate": 1.0,
          "avg_score": 2.0,
          "avg_opponent_score": 1.0,
          "score_differential": 1.0
        },
        "NoPoaching": {
          "wins": 1,
          "total_score": 2,
          "total_opponent_score": 1,
          "win_rate": 1.0,
          "avg_score": 2.0,
          "avg_opponent_score": 1.0,
          "score_differential": 1.0
        },
        "PACT": {
          "wins": 1,
          "total_score": 2,
          "total_opponent_score": 0,
          "win_rate": 1.0,
          "avg_score": 2.0,
          "avg_opponent_score": 0.0,
          "score_differential": 2.0
        },
        "fReya": {
          "wins": 1,
          "total_score": 2,
          "total_opponent_score": 0,
          "win_rate": 1.0,
          "avg_score": 2.0,
          "avg_opponent_score": 0.0,
          "score_differential": 2.0
        },
        "BK ROG Esports": {
          "wins": 0,
          "total_score": 0,
          "total_opponent_score": 2,
          "win_rate": 0.0,
          "avg_score": 0.0,
          "avg_opponent_score": 2.0,
          "score_differential": -2.0
        },
        "MTP Esport": {
          "wins": 1,
          "total_score": 2,
          "total_opponent_score": 0,
          "win_rate": 1.0,
          "avg_score": 2.0,
          "avg_opponent_score": 0.0,
          "score_differential": 2.0
        },
        "Team Bachara": {
          "wins": 1,
          "total_score": 2,
          "total_opponent_score": 0,
          "win_rate": 1.0,
          "avg_score": 2.0,
          "avg_opponent_score": 0.0,
          "score_differential": 2.0
        },
        "Benchwarmers": {
          "wins": 1,
          "total_score": 2,
          "total_opponent_score": 0,
          "win_rate": 1.0,
          "avg_score": 2.0,
          "avg_opponent_score": 0.0,
          "score_differential": 2.0
        },
        "Shanghai Emperors": {
          "wins": 2,
          "total_score": 3,
          "total_opponent_score": 0,
          "win_rate": 1.0,
          "avg_score": 1.5,
          "avg_opponent_score": 0.0,
          "score_differential": 1.5
        },
        "No Witness": {
          "wins": 1,
          "total_score": 2,
          "total_opponent_score": 0,
          "win_rate": 1.0,
          "avg_score": 2.0,
          "avg_opponent_score": 0.0,
          "score_differential": 2.0
        },
        "Team Adios": {
          "wins": 1,
          "total_score": 2,
          "total_opponent_score": 0,
          "win_rate": 1.0,
          "avg_score": 2.0,
          "avg_opponent_score": 0.0,
          "score_differential": 2.0
        },
        "Opportunists": {
          "wins": 0,
          "total_score": 1,
          "total_opponent_score": 2,
          "win_rate": 0.0,
          "avg_score": 1.0,
          "avg_opponent_score": 2.0,
          "score_differential": -1.0
        },
        "Alliance": {
          "wins": 0,
          "total_score": 1,
          "total_opponent_score": 2,
          "win_rate": 0.0,
          "avg_score": 1.0,
          "avg_opponent_score": 2.0,
          "score_differential": -1.0
        },
        "Rix.GG Thunder": {
          "wins": 1,
          "total_score": 2,
          "total_opponent_score": 0,
          "win_rate": 1.0,
          "avg_score": 2.0,
          "avg_opponent_score": 0.0,
          "score_differential": 2.0
        },
        "Entropiq": {
          "wins": 1,
          "total_score": 2,
          "total_opponent_score": 2,
          "win_rate": 0.5,
          "avg_score": 1.0,
          "avg_opponent_score": 1.0,
          "score_differential": 0.0
        },
        "Team 7AM": {
          "wins": 1,
          "total_score": 2,
          "total_opponent_score": 0,
          "win_rate": 1.0,
          "avg_score": 2.0,
          "avg_opponent_score": 0.0,
          "score_differential": 2.0
        },
        "DeftFox": {
          "wins": 1,
          "total_score": 2,
          "total_opponent_score": 0,
          "win_rate": 1.0,
          "avg_score": 2.0,
          "avg_opponent_score": 0.0,
          "score_differential": 2.0
        },
        "Fojosok": {
          "wins": 1,
          "total_score": 2,
          "total_opponent_score": 0,
          "win_rate": 1.0,
          "avg_score": 2.0,
          "avg_opponent_score": 0.0,
          "score_differential": 2.0
        },
        "Acend": {
          "wins": 0,
          "total_score": 2,
          "total_opponent_score": 3,
          "win_rate": 0.0,
          "avg_score": 2.0,
          "avg_opponent_score": 3.0,
          "score_differential": -1.0
        },
        "Guild Esports": {
          "wins": 1,
          "total_score": 2,
          "total_opponent_score": 0,
          "win_rate": 1.0,
          "avg_score": 2.0,
          "avg_opponent_score": 0.0,
          "score_differential": 2.0
        },
        "Ballista": {
          "wins": 1,
          "total_score": 2,
          "total_opponent_score": 0,
          "win_rate": 1.0,
          "avg_score": 2.0,
          "avg_opponent_score": 0.0,
          "score_differential": 2.0
        },
        "OG": {
          "wins": 1,
          "total_score": 2,
          "total_opponent_score": 0,
          "win_rate": 1.0,
          "avg_score": 2.0,
          "avg_opponent_score": 0.0,
          "score_differential": 2.0
        },
        "Chakalaka": {
          "wins": 1,
          "total_score": 2,
          "total_opponent_score": 1,
          "win_rate": 1.0,
          "avg_score": 2.0,
          "avg_opponent_score": 1.0,
          "score_differential": 1.0
        },
        "HSDIRR": {
          "wins": 1,
          "total_score": 2,
          "total_opponent_score": 0,
          "win_rate": 1.0,
          "avg_score": 2.0,
          "avg_opponent_score": 0.0,
          "score_differential": 2.0
        },
        "ESTONOESUNJUEGOVALE": {
          "wins": 1,
          "total_score": 2,
          "total_opponent_score": 0,
          "win_rate": 1.0,
          "avg_score": 2.0,
          "avg_opponent_score": 0.0,
          "score_differential": 2.0
        },
        "Hydrated": {
          "wins": 1,
          "total_score": 2,
          "total_opponent_score": 0,
          "win_rate": 1.0,
          "avg_score": 2.0,
          "avg_opponent_score": 0.0,
          "score_differential": 2.0
        },
        "KET\u00c4": {
          "wins": 1,
          "total_score": 2,
          "total_opponent_score": 0,
          "win_rate": 1.0,
          "avg_score": 2.0,
          "avg_opponent_score": 0.0,
          "score_differential": 2.0
        },
        "Krijgslieden": {
          "wins": 1,
          "total_score": 1,
          "total_opponent_score": 0,
          "win_rate": 1.0,
          "avg_score": 1.0,
          "avg_opponent_score": 0.0,
          "score_differential": 1.0
        },
        "Cream Real Betis": {
          "wins": 2,
          "total_score": 3,
          "total_opponent_score": 0,
          "win_rate": 1.0,
          "avg_score": 1.5,
          "avg_opponent_score": 0.0,
          "score_differential": 1.5
        },
        "FTW Esports": {
          "wins": 1,
          "total_score": 1,
          "total_opponent_score": 0,
          "win_rate": 1.0,
          "avg_score": 1.0,
          "avg_opponent_score": 0.0,
          "score_differential": 1.0
        },
        "need more DM": {
          "wins": 2,
          "total_score": 4,
          "total_opponent_score": 1,
          "win_rate": 1.0,
          "avg_score": 2.0,
          "avg_opponent_score": 0.5,
          "score_differential": 1.5
        },
        "ex-Giants Gaming": {
          "wins": 5,
          "total_score": 9,
          "total_opponent_score": 0,
          "win_rate": 1.0,
          "avg_score": 1.8,
          "avg_opponent_score": 0.0,
          "score_differential": 1.8
        },
        "Wygers": {
          "wins": 2,
          "total_score": 4,
          "total_opponent_score": 0,
          "win_rate": 1.0,
          "avg_score": 2.0,
          "avg_opponent_score": 0.0,
          "score_differential": 2.0
        },
        "SUMN FC": {
          "wins": 1,
          "total_score": 3,
          "total_opponent_score": 1,
          "win_rate": 1.0,
          "avg_score": 3.0,
          "avg_opponent_score": 1.0,
          "score_differential": 2.0
        },
        "hehe_": {
          "wins": 0,
          "total_score": 0,
          "total_opponent_score": 0,
          "win_rate": 0.0,
          "avg_score": 0.0,
          "avg_opponent_score": 0.0,
          "score_differential": 0.0
        },
        "B7 Warriors": {
          "wins": 2,
          "total_score": 4,
          "total_opponent_score": 0,
          "win_rate": 1.0,
          "avg_score": 2.0,
          "avg_opponent_score": 0.0,
          "score_differential": 2.0
        },
        "VASTA Gaming": {
          "wins": 1,
          "total_score": 1,
          "total_opponent_score": 0,
          "win_rate": 1.0,
          "avg_score": 1.0,
          "avg_opponent_score": 0.0,
          "score_differential": 1.0
        },
        "-sheesh-": {
          "wins": 1,
          "total_score": 1,
          "total_opponent_score": 0,
          "win_rate": 1.0,
          "avg_score": 1.0,
          "avg_opponent_score": 0.0,
          "score_differential": 1.0
        },
        "Wave Esports": {
          "wins": 1,
          "total_score": 1,
          "total_opponent_score": 0,
          "win_rate": 1.0,
          "avg_score": 1.0,
          "avg_opponent_score": 0.0,
          "score_differential": 1.0
        },
        "Marten Gaming": {
          "wins": 1,
          "total_score": 1,
          "total_opponent_score": 0,
          "win_rate": 1.0,
          "avg_score": 1.0,
          "avg_opponent_score": 0.0,
          "score_differential": 1.0
        },
        "YkarY eSports": {
          "wins": 1,
          "total_score": 1,
          "total_opponent_score": 0,
          "win_rate": 1.0,
          "avg_score": 1.0,
          "avg_opponent_score": 0.0,
          "score_differential": 1.0
        },
        "STR99": {
          "wins": 1,
          "total_score": 1,
          "total_opponent_score": 0,
          "win_rate": 1.0,
          "avg_score": 1.0,
          "avg_opponent_score": 0.0,
          "score_differential": 1.0
        },
        "L'institut": {
          "wins": 1,
          "total_score": 1,
          "total_opponent_score": 0,
          "win_rate": 1.0,
          "avg_score": 1.0,
          "avg_opponent_score": 0.0,
          "score_differential": 1.0
        },
        "Miracles": {
          "wins": 1,
          "total_score": 1,
          "total_opponent_score": 0,
          "win_rate": 1.0,
          "avg_score": 1.0,
          "avg_opponent_score": 0.0,
          "score_differential": 1.0
        },
        "alltheRAGE": {
          "wins": 1,
          "total_score": 1,
          "total_opponent_score": 0,
          "win_rate": 1.0,
          "avg_score": 1.0,
          "avg_opponent_score": 0.0,
          "score_differential": 1.0
        },
        "ehehxd": {
          "wins": 1,
          "total_score": 1,
          "total_opponent_score": 0,
          "win_rate": 1.0,
          "avg_score": 1.0,
          "avg_opponent_score": 0.0,
          "score_differential": 1.0
        }
      },
      "map_stats": {
        "Unknown": {
          "played": 195,
          "wins": 126,
          "win_rate": 0.6461538461538462
        }
      },
      "advanced_stats": {
        "avg_first_bloods": 0.0,
        "avg_clutches": 0.0,
        "avg_aces": 0.0,
        "avg_entry_kills": 0.0,
        "avg_headshot_percentage": 0.0,
        "avg_kast": 0.0,
        "avg_adr": 0.0,
        "avg_first_kill_diff": 0.0,
        "agent_usage": {}
      },
      "player_stats": {
        "player_count": 5,
        "avg_rating": 1.0459999999999998,
        "avg_acs": 203.3,
        "avg_kd": 1.116,
        "avg_kast": 0.758,
        "avg_adr": 130.78,
        "avg_headshot": 0.382,
        "avg_clutch": 0.148,
        "total_kills": 660,
        "total_deaths": 522,
        "total_assists": 219,
        "total_first_kills": 111,
        "total_first_deaths": 61,
        "agent_usage": {
          "waylay": 1,
          "raze": 1,
          "neon": 1,
          "sova": 1,
          "fade": 1,
          "breach": 1,
          "cypher": 1,
          "viper": 1,
          "vyse": 1,
          "kayo": 1,
          "iso": 1,
          "tejo": 2
        },
        "star_player_rating": 1.27,
        "star_player_name": "MiniBoo",
        "weak_player_rating": 0.6,
        "weak_player_name": "Boo",
        "fk_fd_ratio": 1.819672131147541,
        "team_consistency": 0.4724409448818897
      },
      "avg_player_rating": 1.0459999999999998,
      "avg_player_acs": 203.3,
      "avg_player_kd": 1.116,
      "avg_player_kast": 0.758,
      "avg_player_adr": 130.78,
      "avg_player_headshot": 0.382,
      "star_player_rating": 1.27,
      "team_consistency": 0.4724409448818897,
      "fk_fd_ratio": 1.819672131147541,
      "map_performance": {
        "Unknown": {
          "played": 195,
          "wins": 126,
          "rounds_played": 0,
          "rounds_won": 0,
          "attack_rounds": 0,
          "attack_rounds_won": 0,
          "defense_rounds": 0,
          "defense_rounds_won": 0,
          "overtime_rounds": 0,
          "overtime_rounds_won": 0,
          "win_rate": 0.6461538461538462,
          "round_win_rate": 0,
          "attack_win_rate": 0,
          "defense_win_rate": 0
        }
      },
      "tournament_performance": {
        "VCT 25: EMEA Stage 1:": {
          "played": 4,
          "wins": 4,
          "total_score": 8,
          "total_opponent_score": 2,
          "win_rate": 1.0,
          "avg_score": 2.0,
          "avg_opponent_score": 0.5,
          "score_differential": 1.5,
          "tier": 1
        },
        "VCT 25: EMEA Kickoff:": {
          "played": 4,
          "wins": 2,
          "total_score": 4,
          "total_opponent_score": 6,
          "win_rate": 0.5,
          "avg_score": 1.0,
          "avg_opponent_score": 1.5,
          "score_differential": -0.5,
          "tier": 1
        },
        "HereticsXP #2:": {
          "played": 1,
          "wins": 0,
          "total_score": 0,
          "total_opponent_score": 2,
          "win_rate": 0.0,
          "avg_score": 0.0,
          "avg_opponent_score": 2.0,
          "score_differential": -2.0,
          "tier": 1
        },
        "Red Bull HG #5:": {
          "played": 2,
          "wins": 1,
          "total_score": 1,
          "total_opponent_score": 1,
          "win_rate": 0.5,
          "avg_score": 0.5,
          "avg_opponent_score": 0.5,
          "score_differential": 0.0,
          "tier": 1
        },
        "VCT 2024: Champions:": {
          "played": 8,
          "wins": 6,
          "total_score": 15,
          "total_opponent_score": 10,
          "win_rate": 0.75,
          "avg_score": 1.875,
          "avg_opponent_score": 1.25,
          "score_differential": 0.625,
          "tier": 1
        },
        "VCT 24: EMEA Stage 2:": {
          "played": 8,
          "wins": 6,
          "total_score": 14,
          "total_opponent_score": 8,
          "win_rate": 0.75,
          "avg_score": 1.75,
          "avg_opponent_score": 1.0,
          "score_differential": 0.75,
          "tier": 1
        },
        "VCT 24: Masters Shanghai:": {
          "played": 9,
          "wins": 6,
          "total_score": 17,
          "total_opponent_score": 8,
          "win_rate": 0.6666666666666666,
          "avg_score": 1.8888888888888888,
          "avg_opponent_score": 0.8888888888888888,
          "score_differential": 1.0,
          "tier": 1
        },
        "VCT 24: EMEA Stage 1:": {
          "played": 9,
          "wins": 6,
          "total_score": 15,
          "total_opponent_score": 8,
          "win_rate": 0.6666666666666666,
          "avg_score": 1.6666666666666667,
          "avg_opponent_score": 0.8888888888888888,
          "score_differential": 0.7777777777777779,
          "tier": 1
        },
        "VCT 24: Masters Madrid:": {
          "played": 2,
          "wins": 0,
          "total_score": 2,
          "total_opponent_score": 4,
          "win_rate": 0.0,
          "avg_score": 1.0,
          "avg_opponent_score": 2.0,
          "score_differential": -1.0,
          "tier": 1
        },
        "VCT 24: EMEA Kickoff:": {
          "played": 4,
          "wins": 3,
          "total_score": 7,
          "total_opponent_score": 3,
          "win_rate": 0.75,
          "avg_score": 1.75,
          "avg_opponent_score": 0.75,
          "score_differential": 1.0,
          "tier": 1
        },
        "HereticsXP:": {
          "played": 1,
          "wins": 0,
          "total_score": 0,
          "total_opponent_score": 1,
          "win_rate": 0.0,
          "avg_score": 0.0,
          "avg_opponent_score": 1.0,
          "score_differential": -1.0,
          "tier": 1
        },
        "Crossfire Cup 2023:": {
          "played": 1,
          "wins": 0,
          "total_score": 2,
          "total_opponent_score": 3,
          "win_rate": 0.0,
          "avg_score": 2.0,
          "avg_opponent_score": 3.0,
          "score_differential": -1.0,
          "tier": 1
        },
        "Red Bull HG #4:": {
          "played": 3,
          "wins": 1,
          "total_score": 1,
          "total_opponent_score": 2,
          "win_rate": 0.3333333333333333,
          "avg_score": 0.3333333333333333,
          "avg_opponent_score": 0.6666666666666666,
          "score_differential": -0.3333333333333333,
          "tier": 1
        },
        "VCT 2023: EMEA LCQ:": {
          "played": 1,
          "wins": 0,
          "total_score": 1,
          "total_opponent_score": 2,
          "win_rate": 0.0,
          "avg_score": 1.0,
          "avg_opponent_score": 2.0,
          "score_differential": -1.0,
          "tier": 1
        },
        "VCT 2023: EMEA:": {
          "played": 9,
          "wins": 2,
          "total_score": 7,
          "total_opponent_score": 14,
          "win_rate": 0.2222222222222222,
          "avg_score": 0.7777777777777778,
          "avg_opponent_score": 1.5555555555555556,
          "score_differential": -0.7777777777777778,
          "tier": 1
        },
        "VCT LOCK//IN: S\u00e3o Paulo:": {
          "played": 1,
          "wins": 0,
          "total_score": 0,
          "total_opponent_score": 2,
          "win_rate": 0.0,
          "avg_score": 0.0,
          "avg_opponent_score": 2.0,
          "score_differential": -2.0,
          "tier": 1
        },
        "Red Bull Home Ground #3:": {
          "played": 12,
          "wins": 7,
          "total_score": 9,
          "total_opponent_score": 9,
          "win_rate": 0.5833333333333334,
          "avg_score": 0.75,
          "avg_opponent_score": 0.75,
          "score_differential": 0.0,
          "tier": 1
        },
        "GXR IN Invitational:": {
          "played": 5,
          "wins": 3,
          "total_score": 5,
          "total_opponent_score": 4,
          "win_rate": 0.6,
          "avg_score": 1.0,
          "avg_opponent_score": 0.8,
          "score_differential": 0.19999999999999996,
          "tier": 1
        },
        "Crossfire Cup 2022:": {
          "played": 5,
          "wins": 5,
          "total_score": 11,
          "total_opponent_score": 2,
          "win_rate": 1.0,
          "avg_score": 2.2,
          "avg_opponent_score": 0.4,
          "score_differential": 1.8000000000000003,
          "tier": 1
        },
        "Regional League ES - Stage 2:": {
          "played": 18,
          "wins": 7,
          "total_score": 7,
          "total_opponent_score": 11,
          "win_rate": 0.3888888888888889,
          "avg_score": 0.3888888888888889,
          "avg_opponent_score": 0.6111111111111112,
          "score_differential": -0.22222222222222227,
          "tier": 2
        },
        "Regional League ES:": {
          "played": 11,
          "wins": 3,
          "total_score": 3,
          "total_opponent_score": 8,
          "win_rate": 0.2727272727272727,
          "avg_score": 0.2727272727272727,
          "avg_opponent_score": 0.7272727272727273,
          "score_differential": -0.4545454545454546,
          "tier": 2
        },
        "VCT EU S1: Challengers 2:": {
          "played": 9,
          "wins": 8,
          "total_score": 16,
          "total_opponent_score": 4,
          "win_rate": 0.8888888888888888,
          "avg_score": 1.7777777777777777,
          "avg_opponent_score": 0.4444444444444444,
          "score_differential": 1.3333333333333333,
          "tier": 1
        },
        "VCT EU S1: Challengers 1:": {
          "played": 4,
          "wins": 2,
          "total_score": 4,
          "total_opponent_score": 3,
          "win_rate": 0.5,
          "avg_score": 1.0,
          "avg_opponent_score": 0.75,
          "score_differential": 0.25,
          "tier": 1
        },
        "LVP Rising #3:": {
          "played": 1,
          "wins": 0,
          "total_score": 1,
          "total_opponent_score": 2,
          "win_rate": 0.0,
          "avg_score": 1.0,
          "avg_opponent_score": 2.0,
          "score_differential": -1.0,
          "tier": 1
        },
        "VCT EU S3: Challengers 2:": {
          "played": 8,
          "wins": 6,
          "total_score": 12,
          "total_opponent_score": 8,
          "win_rate": 0.75,
          "avg_score": 1.5,
          "avg_opponent_score": 1.0,
          "score_differential": 0.5,
          "tier": 1
        },
        "VCT EU S3: Challengers 1:": {
          "played": 3,
          "wins": 2,
          "total_score": 4,
          "total_opponent_score": 2,
          "win_rate": 0.6666666666666666,
          "avg_score": 1.3333333333333333,
          "avg_opponent_score": 0.6666666666666666,
          "score_differential": 0.6666666666666666,
          "tier": 1
        },
        "VCT EU S2: Challengers 2:": {
          "played": 5,
          "wins": 4,
          "total_score": 8,
          "total_opponent_score": 2,
          "win_rate": 0.8,
          "avg_score": 1.6,
          "avg_opponent_score": 0.4,
          "score_differential": 1.2000000000000002,
          "tier": 1
        },
        "VCT EU S2: Challengers 1:": {
          "played": 7,
          "wins": 5,
          "total_score": 12,
          "total_opponent_score": 5,
          "win_rate": 0.7142857142857143,
          "avg_score": 1.7142857142857142,
          "avg_opponent_score": 0.7142857142857143,
          "score_differential": 0.9999999999999999,
          "tier": 1
        },
        "VCT EU S1: Masters:": {
          "played": 4,
          "wins": 3,
          "total_score": 8,
          "total_opponent_score": 4,
          "win_rate": 0.75,
          "avg_score": 2.0,
          "avg_opponent_score": 1.0,
          "score_differential": 1.0,
          "tier": 1
        },
        "Valorant Master Series:": {
          "played": 4,
          "wins": 4,
          "total_score": 6,
          "total_opponent_score": 0,
          "win_rate": 1.0,
          "avg_score": 1.5,
          "avg_opponent_score": 0.0,
          "score_differential": 1.5,
          "tier": 1
        },
        "LVP Genesis Cup Radiants:": {
          "played": 5,
          "wins": 4,
          "total_score": 7,
          "total_opponent_score": 1,
          "win_rate": 0.8,
          "avg_score": 1.4,
          "avg_opponent_score": 0.2,
          "score_differential": 1.2,
          "tier": 1
        },
        "First Strike: Europe:": {
          "played": 15,
          "wins": 14,
          "total_score": 19,
          "total_opponent_score": 4,
          "win_rate": 0.9333333333333333,
          "avg_score": 1.2666666666666666,
          "avg_opponent_score": 0.26666666666666666,
          "score_differential": 1.0,
          "tier": 1
        },
        "GameGune 22:": {
          "played": 4,
          "wins": 4,
          "total_score": 8,
          "total_opponent_score": 0,
          "win_rate": 1.0,
          "avg_score": 2.0,
          "avg_opponent_score": 0.0,
          "score_differential": 2.0,
          "tier": 1
        },
        "LVP Genesis Cup Viento:": {
          "played": 4,
          "wins": 4,
          "total_score": 6,
          "total_opponent_score": 0,
          "win_rate": 1.0,
          "avg_score": 1.5,
          "avg_opponent_score": 0.0,
          "score_differential": 1.5,
          "tier": 1
        },
        "LVP Genesis Cup Fuego:": {
          "played": 4,
          "wins": 4,
          "total_score": 6,
          "total_opponent_score": 0,
          "win_rate": 1.0,
          "avg_score": 1.5,
          "avg_opponent_score": 0.0,
          "score_differential": 1.5,
          "tier": 1
        }
      },
      "performance_trends": {
        "recent_matches": {
          "last_5_win_rate": 0.8,
          "last_5_wins": 4,
          "last_5_losses": 1,
          "last_5_avg_score": 1.6,
          "last_5_avg_opp_score": 1.0,
          "last_5_score_diff": 0.6000000000000001,
          "last_10_win_rate": 0.7,
          "last_10_wins": 7,
          "last_10_losses": 3,
          "last_10_avg_score": 1.3,
          "last_10_avg_opp_score": 1.0,
          "last_10_score_diff": 0.30000000000000004,
          "last_20_win_rate": 0.65,
          "last_20_wins": 13,
          "last_20_losses": 7,
          "last_20_avg_score": 1.45,
          "last_20_avg_opp_score": 1.2,
          "last_20_score_diff": 0.25
        },
        "form_trajectory": {
          "5_vs_10": 0.10000000000000009,
          "10_vs_20": 0.04999999999999993
        },
        "progressive_win_rates": [
          {
            "fraction": 0.25,
            "win_rate": 0.9166666666666666
          },
          {
            "fraction": 0.5,
            "win_rate": 0.7319587628865979
          },
          {
            "fraction": 0.75,
            "win_rate": 0.6438356164383562
          },
          {
            "fraction": 1.0,
            "win_rate": 0.6461538461538462
          }
        ],
        "moving_averages": {
          "window_5": [
            1.0,
            1.0,
            1.0,
            1.0,
            1.0,
            1.0,
            1.0,
            0.8,
            0.8,
            0.8,
            0.8,
            0.8,
            1.0,
            1.0,
            1.0,
            1.0,
            1.0,
            1.0,
            1.0,
            1.0,
            1.0,
            0.8,
            0.8,
            0.8,
            0.8,
            0.8,
            1.0,
            1.0,
            1.0,
            1.0,
            1.0,
            1.0,
            0.8,
            0.8,
            0.8,
            0.8,
            0.8,
            1.0,
            1.0,
            1.0,
            1.0,
            1.0,
            1.0,
            0.8,
            0.8,
            0.8,
            0.8,
            0.8,
            0.8,
            0.8,
            0.6,
            0.6,
            0.6,
            0.8,
            0.8,
            0.8,
            0.8,
            0.8,
            0.6,
            0.6,
            0.8,
            0.8,
            0.8,
            1.0,
            0.8,
            0.8,
            0.6,
            0.4,
            0.2,
            0.4,
            0.4,
            0.6,
            0.6,
            0.6,
            0.6,
            0.4,
            0.2,
            0.2,
            0.2,
            0.0,
            0.0,
            0.0,
            0.2,
            0.4,
            0.6,
            0.6,
            0.6,
            0.6,
            0.4,
            0.4,
            0.4,
            0.4,
            0.4,
            0.6,
            0.6,
            0.6,
            0.8,
            0.6,
            0.4,
            0.2,
            0.2,
            0.0,
            0.2,
            0.4,
            0.6,
            0.6,
            0.8,
            0.8,
            0.8,
            0.8,
            1.0,
            0.8,
            0.8,
            0.8,
            0.8,
            0.6,
            0.8,
            0.8,
            0.6,
            0.6,
            0.6,
            0.6,
            0.4,
            0.4,
            0.2,
            0.2,
            0.2,
            0.2,
            0.2,
            0.2,
            0.2,
            0.2,
            0.2,
            0.2,
            0.2,
            0.2,
            0.2,
            0.2,
            0.2,
            0.2,
            0.4,
            0.4,
            0.6,
            0.6,
            0.6,
            0.4,
            0.4,
            0.2,
            0.2,
            0.4,
            0.6,
            0.6,
            0.8,
            1.0,
            0.8,
            0.8,
            0.6,
            0.6,
            0.6,
            0.6,
            0.6,
            0.8,
            0.8,
            0.6,
            0.8,
            0.8,
            0.8,
            0.8,
            1.0,
            0.8,
            0.8,
            0.6,
            0.6,
            0.6,
            0.8,
            0.6,
            0.8,
            0.8,
            0.8,
            0.6,
            0.6,
            0.6,
            0.4,
            0.4,
            0.6,
            0.6,
            0.4,
            0.6,
            0.6,
            0.6,
            0.8
          ],
          "window_5_trend": -0.19999999999999996,
          "window_10": [
            1.0,
            1.0,
            0.9,
            0.9,
            0.9,
            0.9,
            0.9,
            0.9,
            0.9,
            0.9,
            0.9,
            0.9,
            1.0,
            1.0,
            1.0,
            1.0,
            0.9,
            0.9,
            0.9,
            0.9,
            0.9,
            0.9,
            0.9,
            0.9,
            0.9,
            0.9,
            1.0,
            0.9,
            0.9,
            0.9,
            0.9,
            0.9,
            0.9,
            0.9,
            0.9,
            0.9,
            0.9,
            1.0,
            0.9,
            0.9,
            0.9,
            0.9,
            0.9,
            0.8,
            0.8,
            0.7,
            0.7,
            0.7,
            0.8,
            0.8,
            0.7,
            0.7,
            0.7,
            0.7,
            0.7,
            0.8,
            0.8,
            0.8,
            0.8,
            0.7,
            0.8,
            0.7,
            0.6,
            0.6,
            0.6,
            0.6,
            0.6,
            0.5,
            0.4,
            0.5,
            0.4,
            0.4,
            0.4,
            0.4,
            0.3,
            0.2,
            0.1,
            0.2,
            0.3,
            0.3,
            0.3,
            0.3,
            0.4,
            0.4,
            0.5,
            0.5,
            0.5,
            0.5,
            0.5,
            0.5,
            0.5,
            0.6,
            0.5,
            0.5,
            0.4,
            0.4,
            0.4,
            0.4,
            0.4,
            0.4,
            0.4,
            0.4,
            0.5,
            0.6,
            0.7,
            0.8,
            0.8,
            0.8,
            0.8,
            0.8,
            0.8,
            0.8,
            0.8,
            0.7,
            0.7,
            0.6,
            0.7,
            0.6,
            0.5,
            0.4,
            0.4,
            0.4,
            0.3,
            0.3,
            0.2,
            0.2,
            0.2,
            0.2,
            0.2,
            0.2,
            0.2,
            0.2,
            0.2,
            0.2,
            0.2,
            0.3,
            0.3,
            0.4,
            0.4,
            0.4,
            0.4,
            0.4,
            0.4,
            0.4,
            0.5,
            0.5,
            0.5,
            0.5,
            0.6,
            0.6,
            0.7,
            0.6,
            0.7,
            0.8,
            0.7,
            0.7,
            0.7,
            0.7,
            0.6,
            0.7,
            0.7,
            0.8,
            0.8,
            0.8,
            0.8,
            0.8,
            0.7,
            0.7,
            0.8,
            0.8,
            0.7,
            0.7,
            0.7,
            0.7,
            0.7,
            0.6,
            0.7,
            0.6,
            0.6,
            0.6,
            0.6,
            0.5,
            0.5,
            0.5,
            0.6,
            0.7
          ],
          "window_10_trend": -0.30000000000000004,
          "window_20": [
            0.95,
            0.95,
            0.95,
            0.95,
            0.95,
            0.95,
            0.9,
            0.9,
            0.9,
            0.9,
            0.9,
            0.9,
            0.95,
            0.95,
            0.95,
            0.95,
            0.95,
            0.9,
            0.9,
            0.9,
            0.9,
            0.9,
            0.9,
            0.9,
            0.9,
            0.9,
            0.95,
            0.95,
            0.9,
            0.9,
            0.9,
            0.9,
            0.9,
            0.85,
            0.85,
            0.8,
            0.8,
            0.85,
            0.85,
            0.85,
            0.8,
            0.8,
            0.8,
            0.75,
            0.75,
            0.75,
            0.75,
            0.75,
            0.8,
            0.75,
            0.75,
            0.7,
            0.65,
            0.65,
            0.65,
            0.7,
            0.7,
            0.65,
            0.6,
            0.6,
            0.6,
            0.55,
            0.5,
            0.5,
            0.45,
            0.4,
            0.35,
            0.35,
            0.35,
            0.4,
            0.35,
            0.35,
            0.4,
            0.4,
            0.4,
            0.35,
            0.3,
            0.35,
            0.4,
            0.4,
            0.4,
            0.45,
            0.45,
            0.45,
            0.45,
            0.45,
            0.45,
            0.45,
            0.45,
            0.45,
            0.45,
            0.5,
            0.5,
            0.55,
            0.55,
            0.6,
            0.6,
            0.6,
            0.6,
            0.6,
            0.6,
            0.6,
            0.65,
            0.65,
            0.7,
            0.7,
            0.75,
            0.7,
            0.65,
            0.6,
            0.6,
            0.6,
            0.55,
            0.5,
            0.45,
            0.4,
            0.45,
            0.4,
            0.35,
            0.3,
            0.3,
            0.3,
            0.25,
            0.25,
            0.2,
            0.25,
            0.25,
            0.3,
            0.3,
            0.3,
            0.3,
            0.3,
            0.3,
            0.3,
            0.35,
            0.4,
            0.4,
            0.45,
            0.5,
            0.5,
            0.55,
            0.5,
            0.55,
            0.6,
            0.6,
            0.6,
            0.6,
            0.6,
            0.6,
            0.65,
            0.7,
            0.7,
            0.75,
            0.8,
            0.75,
            0.75,
            0.7,
            0.7,
            0.7,
            0.75,
            0.7,
            0.75,
            0.75,
            0.75,
            0.75,
            0.7,
            0.7,
            0.65,
            0.7,
            0.7,
            0.65,
            0.6,
            0.6,
            0.6,
            0.65,
            0.65
          ],
          "window_20_trend": -0.29999999999999993
        },
        "recency_weighted_win_rate": 0.6202614841067485
      },
      "opponent_quality": {
        "avg_opponent_ranking": 0,
        "avg_opponent_rating": 0,
        "top_10_win_rate": 0,
        "top_10_matches": 0,
        "bottom_50_win_rate": 0,
        "bottom_50_matches": 0,
        "upset_factor": 0,
        "upset_vulnerability": 0
      }
    },
    "Team Vitality": {
      "wins": 108,
      "losses": 62,
      "win_rate": 0.6352941176470588,
      "total_score": 232,
      "total_opponent_score": 154,
      "avg_score": 1.3647058823529412,
      "avg_opponent_score": 0.9058823529411765,
      "score_differential": 0.45882352941176474,
      "recent_form": 0.4,
      "opponent_stats": {
        "Apeks": {
          "wins": 1,
          "total_score": 2,
          "total_opponent_score": 0,
          "win_rate": 1.0,
          "avg_score": 2.0,
          "avg_opponent_score": 0.0,
          "score_differential": 2.0
        },
        "Team Heretics": {
          "wins": 7,
          "total_score": 15,
          "total_opponent_score": 5,
          "win_rate": 0.875,
          "avg_score": 1.875,
          "avg_opponent_score": 0.625,
          "score_differential": 1.25
        },
        "FNATIC": {
          "wins": 0,
          "total_score": 3,
          "total_opponent_score": 15,
          "win_rate": 0.0,
          "avg_score": 0.42857142857142855,
          "avg_opponent_score": 2.142857142857143,
          "score_differential": -1.7142857142857142
        },
        "GIANTX": {
          "wins": 2,
          "total_score": 4,
          "total_opponent_score": 1,
          "win_rate": 1.0,
          "avg_score": 2.0,
          "avg_opponent_score": 0.5,
          "score_differential": 1.5
        },
        "T1": {
          "wins": 1,
          "total_score": 3,
          "total_opponent_score": 2,
          "win_rate": 0.5,
          "avg_score": 1.5,
          "avg_opponent_score": 1.0,
          "score_differential": 0.5
        },
        "G2 Esports": {
          "wins": 2,
          "total_score": 6,
          "total_opponent_score": 7,
          "win_rate": 0.4,
          "avg_score": 1.2,
          "avg_opponent_score": 1.4,
          "score_differential": -0.19999999999999996
        },
        "DRX": {
          "wins": 1,
          "total_score": 2,
          "total_opponent_score": 1,
          "win_rate": 1.0,
          "avg_score": 2.0,
          "avg_opponent_score": 1.0,
          "score_differential": 1.0
        },
        "Team Liquid": {
          "wins": 3,
          "total_score": 9,
          "total_opponent_score": 7,
          "win_rate": 0.6,
          "avg_score": 1.8,
          "avg_opponent_score": 1.4,
          "score_differential": 0.40000000000000013
        },
        "FUT Esports": {
          "wins": 3,
          "total_score": 10,
          "total_opponent_score": 11,
          "win_rate": 0.42857142857142855,
          "avg_score": 1.4285714285714286,
          "avg_opponent_score": 1.5714285714285714,
          "score_differential": -0.1428571428571428
        },
        "Karmine Corp": {
          "wins": 6,
          "total_score": 11,
          "total_opponent_score": 6,
          "win_rate": 0.8571428571428571,
          "avg_score": 1.5714285714285714,
          "avg_opponent_score": 0.8571428571428571,
          "score_differential": 0.7142857142857143
        },
        "LEVIAT\u00c1N": {
          "wins": 0,
          "total_score": 0,
          "total_opponent_score": 4,
          "win_rate": 0.0,
          "avg_score": 0.0,
          "avg_opponent_score": 2.0,
          "score_differential": -2.0
        },
        "TALON": {
          "wins": 1,
          "total_score": 2,
          "total_opponent_score": 0,
          "win_rate": 1.0,
          "avg_score": 2.0,
          "avg_opponent_score": 0.0,
          "score_differential": 2.0
        },
        "Trace Esports": {
          "wins": 0,
          "total_score": 1,
          "total_opponent_score": 2,
          "win_rate": 0.0,
          "avg_score": 1.0,
          "avg_opponent_score": 2.0,
          "score_differential": -1.0
        },
        "Natus Vincere": {
          "wins": 1,
          "total_score": 2,
          "total_opponent_score": 7,
          "win_rate": 0.25,
          "avg_score": 0.5,
          "avg_opponent_score": 1.75,
          "score_differential": -1.25
        },
        "BBL Esports": {
          "wins": 1,
          "total_score": 2,
          "total_opponent_score": 3,
          "win_rate": 0.5,
          "avg_score": 1.0,
          "avg_opponent_score": 1.5,
          "score_differential": -0.5
        },
        "KOI": {
          "wins": 3,
          "total_score": 7,
          "total_opponent_score": 2,
          "win_rate": 0.75,
          "avg_score": 1.75,
          "avg_opponent_score": 0.5,
          "score_differential": 1.25
        },
        "Gentle Mates": {
          "wins": 2,
          "total_score": 4,
          "total_opponent_score": 3,
          "win_rate": 0.6666666666666666,
          "avg_score": 1.3333333333333333,
          "avg_opponent_score": 1.0,
          "score_differential": 0.33333333333333326
        },
        "FURIA": {
          "wins": 1,
          "total_score": 2,
          "total_opponent_score": 0,
          "win_rate": 1.0,
          "avg_score": 2.0,
          "avg_opponent_score": 0.0,
          "score_differential": 2.0
        },
        "Global Esports": {
          "wins": 2,
          "total_score": 4,
          "total_opponent_score": 1,
          "win_rate": 1.0,
          "avg_score": 2.0,
          "avg_opponent_score": 0.5,
          "score_differential": 1.5
        },
        "Giants Gaming": {
          "wins": 1,
          "total_score": 3,
          "total_opponent_score": 4,
          "win_rate": 0.3333333333333333,
          "avg_score": 1.0,
          "avg_opponent_score": 1.3333333333333333,
          "score_differential": -0.33333333333333326
        },
        "100 Thieves": {
          "wins": 0,
          "total_score": 0,
          "total_opponent_score": 2,
          "win_rate": 0.0,
          "avg_score": 0.0,
          "avg_opponent_score": 2.0,
          "score_differential": -2.0
        },
        "Cloud9": {
          "wins": 0,
          "total_score": 0,
          "total_opponent_score": 2,
          "win_rate": 0.0,
          "avg_score": 0.0,
          "avg_opponent_score": 2.0,
          "score_differential": -2.0
        },
        "FOKUS": {
          "wins": 1,
          "total_score": 2,
          "total_opponent_score": 1,
          "win_rate": 1.0,
          "avg_score": 2.0,
          "avg_opponent_score": 1.0,
          "score_differential": 1.0
        },
        "KR\u00dc Esports": {
          "wins": 1,
          "total_score": 2,
          "total_opponent_score": 0,
          "win_rate": 1.0,
          "avg_score": 2.0,
          "avg_opponent_score": 0.0,
          "score_differential": 2.0
        },
        "KPI Gaming": {
          "wins": 1,
          "total_score": 2,
          "total_opponent_score": 0,
          "win_rate": 1.0,
          "avg_score": 2.0,
          "avg_opponent_score": 0.0,
          "score_differential": 2.0
        },
        "LANPACAN": {
          "wins": 1,
          "total_score": 2,
          "total_opponent_score": 0,
          "win_rate": 1.0,
          "avg_score": 2.0,
          "avg_opponent_score": 0.0,
          "score_differential": 2.0
        },
        "Case Esports": {
          "wins": 1,
          "total_score": 2,
          "total_opponent_score": 1,
          "win_rate": 1.0,
          "avg_score": 2.0,
          "avg_opponent_score": 1.0,
          "score_differential": 1.0
        },
        "TENSTAR": {
          "wins": 2,
          "total_score": 4,
          "total_opponent_score": 3,
          "win_rate": 0.6666666666666666,
          "avg_score": 1.3333333333333333,
          "avg_opponent_score": 1.0,
          "score_differential": 0.33333333333333326
        },
        "EXCEL": {
          "wins": 1,
          "total_score": 4,
          "total_opponent_score": 4,
          "win_rate": 0.3333333333333333,
          "avg_score": 1.3333333333333333,
          "avg_opponent_score": 1.3333333333333333,
          "score_differential": 0.0
        },
        "MAD Lions": {
          "wins": 1,
          "total_score": 3,
          "total_opponent_score": 2,
          "win_rate": 0.3333333333333333,
          "avg_score": 1.0,
          "avg_opponent_score": 0.6666666666666666,
          "score_differential": 0.33333333333333337
        },
        "Mandatory": {
          "wins": 2,
          "total_score": 3,
          "total_opponent_score": 1,
          "win_rate": 0.6666666666666666,
          "avg_score": 1.0,
          "avg_opponent_score": 0.3333333333333333,
          "score_differential": 0.6666666666666667
        },
        "Valar Morghulis": {
          "wins": 2,
          "total_score": 3,
          "total_opponent_score": 1,
          "win_rate": 0.6666666666666666,
          "avg_score": 1.0,
          "avg_opponent_score": 0.3333333333333333,
          "score_differential": 0.6666666666666667
        },
        "Sector One": {
          "wins": 2,
          "total_score": 3,
          "total_opponent_score": 1,
          "win_rate": 0.6666666666666666,
          "avg_score": 1.0,
          "avg_opponent_score": 0.3333333333333333,
          "score_differential": 0.6666666666666667
        },
        "OG": {
          "wins": 2,
          "total_score": 3,
          "total_opponent_score": 1,
          "win_rate": 0.6666666666666666,
          "avg_score": 1.0,
          "avg_opponent_score": 0.3333333333333333,
          "score_differential": 0.6666666666666667
        },
        "Team BDS": {
          "wins": 3,
          "total_score": 6,
          "total_opponent_score": 7,
          "win_rate": 0.5,
          "avg_score": 1.0,
          "avg_opponent_score": 1.1666666666666667,
          "score_differential": -0.16666666666666674
        },
        "WYLDE": {
          "wins": 2,
          "total_score": 3,
          "total_opponent_score": 1,
          "win_rate": 0.6666666666666666,
          "avg_score": 1.0,
          "avg_opponent_score": 0.3333333333333333,
          "score_differential": 0.6666666666666667
        },
        "beGenius": {
          "wins": 2,
          "total_score": 3,
          "total_opponent_score": 1,
          "win_rate": 0.6666666666666666,
          "avg_score": 1.0,
          "avg_opponent_score": 0.3333333333333333,
          "score_differential": 0.6666666666666667
        },
        "LDN UTD": {
          "wins": 1,
          "total_score": 2,
          "total_opponent_score": 2,
          "win_rate": 0.5,
          "avg_score": 1.0,
          "avg_opponent_score": 1.0,
          "score_differential": 0.0
        },
        "Alliance": {
          "wins": 4,
          "total_score": 9,
          "total_opponent_score": 2,
          "win_rate": 1.0,
          "avg_score": 2.25,
          "avg_opponent_score": 0.5,
          "score_differential": 1.75
        },
        "BIG": {
          "wins": 1,
          "total_score": 2,
          "total_opponent_score": 4,
          "win_rate": 0.5,
          "avg_score": 1.0,
          "avg_opponent_score": 2.0,
          "score_differential": -1.0
        },
        "Guild Esports": {
          "wins": 0,
          "total_score": 0,
          "total_opponent_score": 3,
          "win_rate": 0.0,
          "avg_score": 0.0,
          "avg_opponent_score": 3.0,
          "score_differential": -3.0
        },
        "KOVA": {
          "wins": 1,
          "total_score": 2,
          "total_opponent_score": 0,
          "win_rate": 1.0,
          "avg_score": 2.0,
          "avg_opponent_score": 0.0,
          "score_differential": 2.0
        },
        "Anorthosis Famagusta Esports": {
          "wins": 1,
          "total_score": 2,
          "total_opponent_score": 1,
          "win_rate": 1.0,
          "avg_score": 2.0,
          "avg_opponent_score": 1.0,
          "score_differential": 1.0
        },
        "Kahoot": {
          "wins": 1,
          "total_score": 2,
          "total_opponent_score": 0,
          "win_rate": 1.0,
          "avg_score": 2.0,
          "avg_opponent_score": 0.0,
          "score_differential": 2.0
        },
        "Mercury": {
          "wins": 1,
          "total_score": 2,
          "total_opponent_score": 0,
          "win_rate": 1.0,
          "avg_score": 2.0,
          "avg_opponent_score": 0.0,
          "score_differential": 2.0
        },
        "Orkestra": {
          "wins": 1,
          "total_score": 2,
          "total_opponent_score": 0,
          "win_rate": 1.0,
          "avg_score": 2.0,
          "avg_opponent_score": 0.0,
          "score_differential": 2.0
        },
        "Stunned5": {
          "wins": 1,
          "total_score": 2,
          "total_opponent_score": 0,
          "win_rate": 1.0,
          "avg_score": 2.0,
          "avg_opponent_score": 0.0,
          "score_differential": 2.0
        },
        "Last Dance": {
          "wins": 1,
          "total_score": 4,
          "total_opponent_score": 3,
          "win_rate": 0.5,
          "avg_score": 2.0,
          "avg_opponent_score": 1.5,
          "score_differential": 0.5
        },
        "BK ROG Esports": {
          "wins": 3,
          "total_score": 6,
          "total_opponent_score": 0,
          "win_rate": 1.0,
          "avg_score": 2.0,
          "avg_opponent_score": 0.0,
          "score_differential": 2.0
        },
        "NOX Esports": {
          "wins": 1,
          "total_score": 2,
          "total_opponent_score": 0,
          "win_rate": 1.0,
          "avg_score": 2.0,
          "avg_opponent_score": 0.0,
          "score_differential": 2.0
        },
        "Exalty": {
          "wins": 1,
          "total_score": 2,
          "total_opponent_score": 0,
          "win_rate": 1.0,
          "avg_score": 2.0,
          "avg_opponent_score": 0.0,
          "score_differential": 2.0
        },
        "Ninjas in Pyjamas": {
          "wins": 1,
          "total_score": 2,
          "total_opponent_score": 1,
          "win_rate": 1.0,
          "avg_score": 2.0,
          "avg_opponent_score": 1.0,
          "score_differential": 1.0
        },
        "Wave Esports": {
          "wins": 1,
          "total_score": 3,
          "total_opponent_score": 2,
          "win_rate": 0.5,
          "avg_score": 1.5,
          "avg_opponent_score": 1.0,
          "score_differential": 0.5
        },
        "WiLD MultiGaming": {
          "wins": 1,
          "total_score": 2,
          "total_opponent_score": 1,
          "win_rate": 1.0,
          "avg_score": 2.0,
          "avg_opponent_score": 1.0,
          "score_differential": 1.0
        },
        "FunPlus Phoenix": {
          "wins": 0,
          "total_score": 0,
          "total_opponent_score": 4,
          "win_rate": 0.0,
          "avg_score": 0.0,
          "avg_opponent_score": 2.0,
          "score_differential": -2.0
        },
        "Entropiq": {
          "wins": 1,
          "total_score": 2,
          "total_opponent_score": 0,
          "win_rate": 1.0,
          "avg_score": 2.0,
          "avg_opponent_score": 0.0,
          "score_differential": 2.0
        },
        "Megastitut": {
          "wins": 0,
          "total_score": 1,
          "total_opponent_score": 3,
          "win_rate": 0.0,
          "avg_score": 1.0,
          "avg_opponent_score": 3.0,
          "score_differential": -2.0
        },
        "UBITEAM": {
          "wins": 2,
          "total_score": 4,
          "total_opponent_score": 0,
          "win_rate": 1.0,
          "avg_score": 2.0,
          "avg_opponent_score": 0.0,
          "score_differential": 2.0
        },
        "Acend": {
          "wins": 1,
          "total_score": 2,
          "total_opponent_score": 2,
          "win_rate": 0.5,
          "avg_score": 1.0,
          "avg_opponent_score": 1.0,
          "score_differential": 0.0
        },
        "Tarren Mill": {
          "wins": 1,
          "total_score": 2,
          "total_opponent_score": 0,
          "win_rate": 1.0,
          "avg_score": 2.0,
          "avg_opponent_score": 0.0,
          "score_differential": 2.0
        },
        "Sprayz Gaming": {
          "wins": 1,
          "total_score": 2,
          "total_opponent_score": 0,
          "win_rate": 1.0,
          "avg_score": 2.0,
          "avg_opponent_score": 0.0,
          "score_differential": 2.0
        },
        "DIVAN": {
          "wins": 1,
          "total_score": 2,
          "total_opponent_score": 0,
          "win_rate": 1.0,
          "avg_score": 2.0,
          "avg_opponent_score": 0.0,
          "score_differential": 2.0
        },
        "KLATWA": {
          "wins": 1,
          "total_score": 2,
          "total_opponent_score": 1,
          "win_rate": 1.0,
          "avg_score": 2.0,
          "avg_opponent_score": 1.0,
          "score_differential": 1.0
        },
        "Patchwork": {
          "wins": 2,
          "total_score": 4,
          "total_opponent_score": 1,
          "win_rate": 1.0,
          "avg_score": 2.0,
          "avg_opponent_score": 0.5,
          "score_differential": 1.5
        },
        "Circe": {
          "wins": 1,
          "total_score": 2,
          "total_opponent_score": 0,
          "win_rate": 1.0,
          "avg_score": 2.0,
          "avg_opponent_score": 0.0,
          "score_differential": 2.0
        },
        "Vertical Seven Esports": {
          "wins": 1,
          "total_score": 2,
          "total_opponent_score": 0,
          "win_rate": 1.0,
          "avg_score": 2.0,
          "avg_opponent_score": 0.0,
          "score_differential": 2.0
        },
        "Raise Your Edge": {
          "wins": 0,
          "total_score": 0,
          "total_opponent_score": 2,
          "win_rate": 0.0,
          "avg_score": 0.0,
          "avg_opponent_score": 2.0,
          "score_differential": -2.0
        },
        "Team Galaga": {
          "wins": 1,
          "total_score": 2,
          "total_opponent_score": 0,
          "win_rate": 1.0,
          "avg_score": 2.0,
          "avg_opponent_score": 0.0,
          "score_differential": 2.0
        },
        "volvo peek": {
          "wins": 1,
          "total_score": 2,
          "total_opponent_score": 0,
          "win_rate": 1.0,
          "avg_score": 2.0,
          "avg_opponent_score": 0.0,
          "score_differential": 2.0
        },
        "unsigned": {
          "wins": 1,
          "total_score": 2,
          "total_opponent_score": 1,
          "win_rate": 1.0,
          "avg_score": 2.0,
          "avg_opponent_score": 1.0,
          "score_differential": 1.0
        },
        "Swag Silicone": {
          "wins": 2,
          "total_score": 2,
          "total_opponent_score": 0,
          "win_rate": 1.0,
          "avg_score": 1.0,
          "avg_opponent_score": 0.0,
          "score_differential": 1.0
        },
        "NoNamers": {
          "wins": 1,
          "total_score": 1,
          "total_opponent_score": 0,
          "win_rate": 1.0,
          "avg_score": 1.0,
          "avg_opponent_score": 0.0,
          "score_differential": 1.0
        },
        "Team LEISURE": {
          "wins": 0,
          "total_score": 0,
          "total_opponent_score": 0,
          "win_rate": 0.0,
          "avg_score": 0.0,
          "avg_opponent_score": 0.0,
          "score_differential": 0.0
        },
        "The Goose House": {
          "wins": 1,
          "total_score": 1,
          "total_opponent_score": 0,
          "win_rate": 1.0,
          "avg_score": 1.0,
          "avg_opponent_score": 0.0,
          "score_differential": 1.0
        },
        "iPon Esport": {
          "wins": 0,
          "total_score": 1,
          "total_opponent_score": 2,
          "win_rate": 0.0,
          "avg_score": 1.0,
          "avg_opponent_score": 2.0,
          "score_differential": -1.0
        },
        "chess on crack": {
          "wins": 1,
          "total_score": 2,
          "total_opponent_score": 0,
          "win_rate": 1.0,
          "avg_score": 2.0,
          "avg_opponent_score": 0.0,
          "score_differential": 2.0
        },
        "stay Focused": {
          "wins": 1,
          "total_score": 2,
          "total_opponent_score": 0,
          "win_rate": 1.0,
          "avg_score": 2.0,
          "avg_opponent_score": 0.0,
          "score_differential": 2.0
        },
        "Monkey Business": {
          "wins": 0,
          "total_score": 0,
          "total_opponent_score": 2,
          "win_rate": 0.0,
          "avg_score": 0.0,
          "avg_opponent_score": 2.0,
          "score_differential": -2.0
        },
        "playzone": {
          "wins": 1,
          "total_score": 2,
          "total_opponent_score": 0,
          "win_rate": 1.0,
          "avg_score": 2.0,
          "avg_opponent_score": 0.0,
          "score_differential": 2.0
        },
        "UCAM Esports Club": {
          "wins": 1,
          "total_score": 1,
          "total_opponent_score": 0,
          "win_rate": 1.0,
          "avg_score": 1.0,
          "avg_opponent_score": 0.0,
          "score_differential": 1.0
        },
        "Hajty": {
          "wins": 1,
          "total_score": 1,
          "total_opponent_score": 0,
          "win_rate": 1.0,
          "avg_score": 1.0,
          "avg_opponent_score": 0.0,
          "score_differential": 1.0
        },
        "FrenzyGoKill": {
          "wins": 1,
          "total_score": 5,
          "total_opponent_score": 8,
          "win_rate": 0.25,
          "avg_score": 1.25,
          "avg_opponent_score": 2.0,
          "score_differential": -0.75
        }
      },
      "map_stats": {
        "Unknown": {
          "played": 170,
          "wins": 108,
          "win_rate": 0.6352941176470588
        }
      },
      "advanced_stats": {
        "avg_first_bloods": 0.0,
        "avg_clutches": 0.0,
        "avg_aces": 0.0,
        "avg_entry_kills": 0.0,
        "avg_headshot_percentage": 0.0,
        "avg_kast": 0.0,
        "avg_adr": 0.0,
        "avg_first_kill_diff": 0.0,
        "agent_usage": {}
      },
      "player_stats": {
        "player_count": 5,
        "avg_rating": 0.994,
        "avg_acs": 191.64000000000001,
        "avg_kd": 0.974,
        "avg_kast": 0.718,
        "avg_adr": 114.23999999999998,
        "avg_headshot": 0.242,
        "avg_clutch": 0.22400000000000003,
        "total_kills": 1278,
        "total_deaths": 1263,
        "total_assists": 588,
        "total_first_kills": 179,
        "total_first_deaths": 194,
        "agent_usage": {
          "breach": 2,
          "skye": 1,
          "omen": 3,
          "astra": 1,
          "tejo": 2,
          "kayo": 1,
          "raze": 1,
          "jett": 1,
          "yoru": 1,
          "vyse": 1
        },
        "star_player_rating": 1.17,
        "star_player_name": "CyvOph",
        "weak_player_rating": 0.84,
        "weak_player_name": "Sayf",
        "fk_fd_ratio": 0.9226804123711341,
        "team_consistency": 0.717948717948718
      },
      "avg_player_rating": 0.994,
      "avg_player_acs": 191.64000000000001,
      "avg_player_kd": 0.974,
      "avg_player_kast": 0.718,
      "avg_player_adr": 114.23999999999998,
      "avg_player_headshot": 0.242,
      "star_player_rating": 1.17,
      "team_consistency": 0.717948717948718,
      "fk_fd_ratio": 0.9226804123711341,
      "map_performance": {
        "Unknown": {
          "played": 170,
          "wins": 108,
          "rounds_played": 0,
          "rounds_won": 0,
          "attack_rounds": 0,
          "attack_rounds_won": 0,
          "defense_rounds": 0,
          "defense_rounds_won": 0,
          "overtime_rounds": 0,
          "overtime_rounds_won": 0,
          "win_rate": 0.6352941176470588,
          "round_win_rate": 0,
          "attack_win_rate": 0,
          "defense_win_rate": 0
        }
      },
      "tournament_performance": {
        "VCT 25: EMEA Stage 1:": {
          "played": 4,
          "wins": 2,
          "total_score": 5,
          "total_opponent_score": 4,
          "win_rate": 0.5,
          "avg_score": 1.25,
          "avg_opponent_score": 1.0,
          "score_differential": 0.25,
          "tier": 1
        },
        "VCT 25: Masters Bangkok:": {
          "played": 4,
          "wins": 2,
          "total_score": 5,
          "total_opponent_score": 5,
          "win_rate": 0.5,
          "avg_score": 1.25,
          "avg_opponent_score": 1.25,
          "score_differential": 0.0,
          "tier": 1
        },
        "VCT 25: EMEA Kickoff:": {
          "played": 4,
          "wins": 4,
          "total_score": 9,
          "total_opponent_score": 3,
          "win_rate": 1.0,
          "avg_score": 2.25,
          "avg_opponent_score": 0.75,
          "score_differential": 1.5,
          "tier": 1
        },
        "VCT 2024: Champions:": {
          "played": 3,
          "wins": 1,
          "total_score": 3,
          "total_opponent_score": 4,
          "win_rate": 0.3333333333333333,
          "avg_score": 1.0,
          "avg_opponent_score": 1.3333333333333333,
          "score_differential": -0.33333333333333326,
          "tier": 1
        },
        "VCT 24: EMEA Stage 2:": {
          "played": 9,
          "wins": 6,
          "total_score": 15,
          "total_opponent_score": 12,
          "win_rate": 0.6666666666666666,
          "avg_score": 1.6666666666666667,
          "avg_opponent_score": 1.3333333333333333,
          "score_differential": 0.3333333333333335,
          "tier": 1
        },
        "VCT 24: EMEA Stage 1:": {
          "played": 6,
          "wins": 3,
          "total_score": 7,
          "total_opponent_score": 9,
          "win_rate": 0.5,
          "avg_score": 1.1666666666666667,
          "avg_opponent_score": 1.5,
          "score_differential": -0.33333333333333326,
          "tier": 1
        },
        "VCT 24: EMEA Kickoff:": {
          "played": 5,
          "wins": 3,
          "total_score": 6,
          "total_opponent_score": 5,
          "win_rate": 0.6,
          "avg_score": 1.2,
          "avg_opponent_score": 1.0,
          "score_differential": 0.19999999999999996,
          "tier": 1
        },
        "Convergence 2023:": {
          "played": 3,
          "wins": 2,
          "total_score": 5,
          "total_opponent_score": 3,
          "win_rate": 0.6666666666666666,
          "avg_score": 1.6666666666666667,
          "avg_opponent_score": 1.0,
          "score_differential": 0.6666666666666667,
          "tier": 1
        },
        "VCT 2023: EMEA:": {
          "played": 11,
          "wins": 4,
          "total_score": 11,
          "total_opponent_score": 15,
          "win_rate": 0.36363636363636365,
          "avg_score": 1.0,
          "avg_opponent_score": 1.3636363636363635,
          "score_differential": -0.36363636363636354,
          "tier": 1
        },
        "VCT LOCK//IN: S\u00e3o Paulo:": {
          "played": 2,
          "wins": 1,
          "total_score": 2,
          "total_opponent_score": 3,
          "win_rate": 0.5,
          "avg_score": 1.0,
          "avg_opponent_score": 1.5,
          "score_differential": -0.5,
          "tier": 1
        },
        "Red Bull Home Ground #3:": {
          "played": 5,
          "wins": 3,
          "total_score": 6,
          "total_opponent_score": 5,
          "win_rate": 0.6,
          "avg_score": 1.2,
          "avg_opponent_score": 1.0,
          "score_differential": 0.19999999999999996,
          "tier": 1
        },
        "G-Loot Clash:": {
          "played": 3,
          "wins": 2,
          "total_score": 4,
          "total_opponent_score": 2,
          "win_rate": 0.6666666666666666,
          "avg_score": 1.3333333333333333,
          "avg_opponent_score": 0.6666666666666666,
          "score_differential": 0.6666666666666666,
          "tier": 1
        },
        "VRL 2022: Finals:": {
          "played": 6,
          "wins": 4,
          "total_score": 10,
          "total_opponent_score": 6,
          "win_rate": 0.6666666666666666,
          "avg_score": 1.6666666666666667,
          "avg_opponent_score": 1.0,
          "score_differential": 0.6666666666666667,
          "tier": 1
        },
        "Regional League FR: Revolution - Stage 2:": {
          "played": 20,
          "wins": 16,
          "total_score": 20,
          "total_opponent_score": 6,
          "win_rate": 0.8,
          "avg_score": 1.0,
          "avg_opponent_score": 0.3,
          "score_differential": 0.7,
          "tier": 2
        },
        "Regional League FR:": {
          "played": 7,
          "wins": 1,
          "total_score": 7,
          "total_opponent_score": 7,
          "win_rate": 0.14285714285714285,
          "avg_score": 1.0,
          "avg_opponent_score": 1.0,
          "score_differential": 0.0,
          "tier": 2
        },
        "VCT EU S1: Challengers 2:": {
          "played": 7,
          "wins": 4,
          "total_score": 10,
          "total_opponent_score": 7,
          "win_rate": 0.5714285714285714,
          "avg_score": 1.4285714285714286,
          "avg_opponent_score": 1.0,
          "score_differential": 0.4285714285714286,
          "tier": 1
        },
        "VCT EU S1: Challengers 1:": {
          "played": 15,
          "wins": 12,
          "total_score": 21,
          "total_opponent_score": 10,
          "win_rate": 0.8,
          "avg_score": 1.4,
          "avg_opponent_score": 0.6666666666666666,
          "score_differential": 0.7333333333333333,
          "tier": 1
        },
        "VOT France: Main Event:": {
          "played": 3,
          "wins": 3,
          "total_score": 8,
          "total_opponent_score": 3,
          "win_rate": 1.0,
          "avg_score": 2.6666666666666665,
          "avg_opponent_score": 1.0,
          "score_differential": 1.6666666666666665,
          "tier": 1
        },
        "VOT France: Fall Qualifier:": {
          "played": 7,
          "wins": 6,
          "total_score": 14,
          "total_opponent_score": 3,
          "win_rate": 0.8571428571428571,
          "avg_score": 2.0,
          "avg_opponent_score": 0.42857142857142855,
          "score_differential": 1.5714285714285714,
          "tier": 1
        },
        "VCT EU S3: Challengers 2:": {
          "played": 7,
          "wins": 4,
          "total_score": 9,
          "total_opponent_score": 8,
          "win_rate": 0.5714285714285714,
          "avg_score": 1.2857142857142858,
          "avg_opponent_score": 1.1428571428571428,
          "score_differential": 0.14285714285714302,
          "tier": 1
        },
        "VCT EU S3: Challengers 1:": {
          "played": 3,
          "wins": 1,
          "total_score": 3,
          "total_opponent_score": 5,
          "win_rate": 0.3333333333333333,
          "avg_score": 1.0,
          "avg_opponent_score": 1.6666666666666667,
          "score_differential": -0.6666666666666667,
          "tier": 1
        },
        "VOT France: Spring Qualifier:": {
          "played": 7,
          "wins": 5,
          "total_score": 12,
          "total_opponent_score": 5,
          "win_rate": 0.7142857142857143,
          "avg_score": 1.7142857142857142,
          "avg_opponent_score": 0.7142857142857143,
          "score_differential": 0.9999999999999999,
          "tier": 1
        },
        "VCT EU S2: Challengers 2:": {
          "played": 8,
          "wins": 6,
          "total_score": 13,
          "total_opponent_score": 4,
          "win_rate": 0.75,
          "avg_score": 1.625,
          "avg_opponent_score": 0.5,
          "score_differential": 1.125,
          "tier": 1
        },
        "VCT EU S2: Challengers 1:": {
          "played": 7,
          "wins": 5,
          "total_score": 10,
          "total_opponent_score": 7,
          "win_rate": 0.7142857142857143,
          "avg_score": 1.4285714285714286,
          "avg_opponent_score": 1.0,
          "score_differential": 0.4285714285714286,
          "tier": 1
        },
        "VCT EU S1: Challengers 3:": {
          "played": 2,
          "wins": 1,
          "total_score": 2,
          "total_opponent_score": 2,
          "win_rate": 0.5,
          "avg_score": 1.0,
          "avg_opponent_score": 1.0,
          "score_differential": 0.0,
          "tier": 1
        },
        "epic32:": {
          "played": 8,
          "wins": 6,
          "total_score": 10,
          "total_opponent_score": 3,
          "win_rate": 0.75,
          "avg_score": 1.25,
          "avg_opponent_score": 0.375,
          "score_differential": 0.875,
          "tier": 1
        },
        "Red Bull Home Ground:": {
          "played": 4,
          "wins": 1,
          "total_score": 5,
          "total_opponent_score": 8,
          "win_rate": 0.25,
          "avg_score": 1.25,
          "avg_opponent_score": 2.0,
          "score_differential": -0.75,
          "tier": 1
        }
      },
      "performance_trends": {
        "recent_matches": {
          "last_5_win_rate": 0.4,
          "last_5_wins": 2,
          "last_5_losses": 3,
          "last_5_avg_score": 1.2,
          "last_5_avg_opp_score": 1.2,
          "last_5_score_diff": 0.0,
          "last_10_win_rate": 0.6,
          "last_10_wins": 6,
          "last_10_losses": 4,
          "last_10_avg_score": 1.5,
          "last_10_avg_opp_score": 1.1,
          "last_10_score_diff": 0.3999999999999999,
          "last_20_win_rate": 0.6,
          "last_20_wins": 12,
          "last_20_losses": 8,
          "last_20_avg_score": 1.5,
          "last_20_avg_opp_score": 1.2,
          "last_20_score_diff": 0.30000000000000004
        },
        "form_trajectory": {
          "5_vs_10": -0.19999999999999996,
          "10_vs_20": 0.0
        },
        "progressive_win_rates": [
          {
            "fraction": 0.25,
            "win_rate": 0.6904761904761905
          },
          {
            "fraction": 0.5,
            "win_rate": 0.6470588235294118
          },
          {
            "fraction": 0.75,
            "win_rate": 0.6614173228346457
          },
          {
            "fraction": 1.0,
            "win_rate": 0.6352941176470588
          }
        ],
        "moving_averages": {
          "window_5": [
            0.4,
            0.6,
            0.8,
            0.8,
            0.8,
            0.8,
            0.8,
            0.6,
            0.8,
            0.8,
            0.8,
            0.6,
            0.8,
            0.6,
            0.6,
            0.6,
            0.6,
            0.6,
            0.8,
            0.8,
            0.8,
            1.0,
            0.8,
            0.8,
            0.6,
            0.6,
            0.6,
            0.8,
            0.8,
            0.8,
            0.8,
            0.8,
            0.6,
            0.6,
            0.8,
            0.8,
            0.8,
            0.8,
            0.8,
            0.6,
            0.4,
            0.4,
            0.4,
            0.4,
            0.6,
            0.6,
            0.6,
            0.8,
            0.6,
            0.4,
            0.6,
            0.6,
            0.6,
            0.8,
            1.0,
            0.8,
            0.8,
            0.8,
            0.8,
            0.8,
            1.0,
            1.0,
            1.0,
            1.0,
            1.0,
            1.0,
            1.0,
            1.0,
            0.8,
            0.6,
            0.4,
            0.4,
            0.2,
            0.4,
            0.6,
            0.6,
            0.4,
            0.4,
            0.2,
            0.0,
            0.0,
            0.2,
            0.2,
            0.2,
            0.2,
            0.4,
            0.4,
            0.6,
            0.8,
            1.0,
            1.0,
            1.0,
            0.8,
            0.8,
            0.8,
            0.8,
            0.8,
            1.0,
            1.0,
            1.0,
            1.0,
            0.8,
            0.8,
            0.8,
            0.8,
            0.8,
            0.8,
            0.8,
            0.8,
            0.6,
            0.4,
            0.6,
            0.6,
            0.4,
            0.6,
            0.8,
            0.6,
            0.6,
            0.8,
            0.6,
            0.6,
            0.6,
            0.4,
            0.2,
            0.2,
            0.2,
            0.2,
            0.2,
            0.4,
            0.6,
            0.4,
            0.6,
            0.6,
            0.6,
            0.6,
            0.6,
            0.4,
            0.6,
            0.6,
            0.4,
            0.6,
            0.6,
            0.6,
            0.4,
            0.6,
            0.6,
            0.8,
            0.8,
            0.8,
            0.8,
            0.6,
            0.4,
            0.4,
            0.4,
            0.4,
            0.6,
            0.8,
            0.8,
            1.0,
            1.0,
            0.8,
            0.6,
            0.6,
            0.4,
            0.2,
            0.4
          ],
          "window_5_trend": 0.0,
          "window_10": [
            0.6,
            0.7,
            0.7,
            0.8,
            0.8,
            0.8,
            0.7,
            0.7,
            0.7,
            0.7,
            0.7,
            0.6,
            0.7,
            0.7,
            0.7,
            0.7,
            0.8,
            0.7,
            0.8,
            0.7,
            0.7,
            0.8,
            0.8,
            0.8,
            0.7,
            0.7,
            0.7,
            0.7,
            0.7,
            0.8,
            0.8,
            0.8,
            0.7,
            0.7,
            0.7,
            0.6,
            0.6,
            0.6,
            0.6,
            0.6,
            0.5,
            0.5,
            0.6,
            0.5,
            0.5,
            0.6,
            0.6,
            0.7,
            0.7,
            0.7,
            0.7,
            0.7,
            0.7,
            0.8,
            0.9,
            0.9,
            0.9,
            0.9,
            0.9,
            0.9,
            1.0,
            1.0,
            1.0,
            0.9,
            0.8,
            0.7,
            0.7,
            0.6,
            0.6,
            0.6,
            0.5,
            0.4,
            0.3,
            0.3,
            0.3,
            0.3,
            0.3,
            0.3,
            0.2,
            0.1,
            0.2,
            0.3,
            0.4,
            0.5,
            0.6,
            0.7,
            0.7,
            0.7,
            0.8,
            0.9,
            0.9,
            0.9,
            0.9,
            0.9,
            0.9,
            0.9,
            0.8,
            0.9,
            0.9,
            0.9,
            0.9,
            0.8,
            0.8,
            0.8,
            0.7,
            0.6,
            0.7,
            0.7,
            0.6,
            0.6,
            0.6,
            0.6,
            0.6,
            0.6,
            0.6,
            0.7,
            0.6,
            0.5,
            0.5,
            0.4,
            0.4,
            0.4,
            0.3,
            0.3,
            0.4,
            0.3,
            0.4,
            0.4,
            0.5,
            0.6,
            0.5,
            0.5,
            0.6,
            0.6,
            0.5,
            0.6,
            0.5,
            0.6,
            0.5,
            0.5,
            0.6,
            0.7,
            0.7,
            0.6,
            0.7,
            0.6,
            0.6,
            0.6,
            0.6,
            0.6,
            0.6,
            0.6,
            0.6,
            0.7,
            0.7,
            0.7,
            0.7,
            0.7,
            0.7,
            0.6,
            0.6
          ],
          "window_10_trend": 0.0,
          "window_20": [
            0.65,
            0.65,
            0.7,
            0.75,
            0.75,
            0.75,
            0.75,
            0.7,
            0.75,
            0.7,
            0.7,
            0.7,
            0.75,
            0.75,
            0.7,
            0.7,
            0.75,
            0.7,
            0.75,
            0.75,
            0.75,
            0.8,
            0.75,
            0.75,
            0.7,
            0.65,
            0.65,
            0.65,
            0.65,
            0.7,
            0.65,
            0.65,
            0.65,
            0.6,
            0.6,
            0.6,
            0.6,
            0.65,
            0.65,
            0.65,
            0.6,
            0.6,
            0.65,
            0.65,
            0.7,
            0.75,
            0.75,
            0.8,
            0.8,
            0.8,
            0.85,
            0.85,
            0.85,
            0.85,
            0.85,
            0.8,
            0.8,
            0.75,
            0.75,
            0.75,
            0.75,
            0.7,
            0.65,
            0.6,
            0.55,
            0.5,
            0.5,
            0.45,
            0.4,
            0.35,
            0.35,
            0.35,
            0.35,
            0.4,
            0.45,
            0.5,
            0.5,
            0.5,
            0.5,
            0.5,
            0.55,
            0.6,
            0.65,
            0.7,
            0.75,
            0.8,
            0.75,
            0.8,
            0.85,
            0.9,
            0.9,
            0.85,
            0.85,
            0.85,
            0.8,
            0.75,
            0.75,
            0.8,
            0.75,
            0.75,
            0.75,
            0.7,
            0.7,
            0.7,
            0.65,
            0.65,
            0.65,
            0.6,
            0.55,
            0.5,
            0.5,
            0.5,
            0.45,
            0.45,
            0.5,
            0.5,
            0.5,
            0.45,
            0.5,
            0.5,
            0.45,
            0.45,
            0.45,
            0.45,
            0.45,
            0.45,
            0.45,
            0.5,
            0.5,
            0.55,
            0.55,
            0.6,
            0.65,
            0.6,
            0.6,
            0.6,
            0.55,
            0.6,
            0.55,
            0.55,
            0.6,
            0.65,
            0.65,
            0.65,
            0.7,
            0.65,
            0.65,
            0.65,
            0.65,
            0.6,
            0.6
          ],
          "window_20_trend": -0.050000000000000044
        },
        "recency_weighted_win_rate": 0.6239131618019816
      },
      "opponent_quality": {
        "avg_opponent_ranking": 0,
        "avg_opponent_rating": 0,
        "top_10_win_rate": 0,
        "top_10_matches": 0,
        "bottom_50_win_rate": 0,
        "bottom_50_matches": 0,
        "upset_factor": 0,
        "upset_vulnerability": 0
      }
    }
  },
  "analysis": {
    "key_factors": [
      "Team Heretics has better recent form (80.0% vs 40.0%)",
      "Team Vitality has historically dominated this matchup (87.5% win rate in 8 matches)"
    ],
    "head_to_head": {
      "matches_played": 8,
      "team1_win_rate": 0.125,
      "team2_win_rate": 0.875
    },
    "map_analysis": {
      "Unknown": {
        "Team Heretics_win_rate": 0.6461538461538462,
        "Team Vitality_win_rate": 0.6352941176470588,
        "advantage": "neutral"
      }
    },
    "player_comparison": {
      "avg_rating": {
        "Team Heretics": 1.0459999999999998,
        "Team Vitality": 0.994,
        "difference": 0.051999999999999824
      },
      "avg_acs": {
        "Team Heretics": 203.3,
        "Team Vitality": 191.64000000000001,
        "difference": 11.659999999999997
      },
      "avg_kd": {
        "Team Heretics": 1.116,
        "Team Vitality": 0.974,
        "difference": 0.14200000000000013
      },
      "fk_fd_ratio": {
        "Team Heretics": 1.819672131147541,
        "Team Vitality": 0.9226804123711341,
        "difference": 0.8969917187764069
      },
      "star_players": {
        "Team Heretics": {
          "name": "MiniBoo",
          "rating": 1.27
        },
        "Team Vitality": {
          "name": "CyvOph",
          "rating": 1.17
        }
      }
    }
  }
}