{
    "feature_names": [
        "team1_matches",
        "team1_wins",
        "team1_win_rate",
        "team1_avg_score",
        "team1_score_diff",
        "team2_matches",
        "team2_wins",
        "team2_win_rate",
        "team2_avg_score",
        "team2_score_diff",
        "team1_ranking",
        "team2_ranking",
        "team1_rating",
        "team2_rating",
        "team1_recent_form_5",
        "team1_recent_form_10",
        "team1_form_trajectory",
        "team1_recency_weighted_win_rate",
        "team2_recent_form_5",
        "team2_recent_form_10",
        "team2_form_trajectory",
        "team2_recency_weighted_win_rate",
        "team1_lan_win_rate",
        "team1_online_win_rate",
        "team1_lan_vs_online_diff",
        "team2_lan_win_rate",
        "team2_online_win_rate",
        "team2_lan_vs_online_diff",
        "team1_avg_opponent_ranking",
        "team1_top_10_win_rate",
        "team1_upset_factor",
        "team2_avg_opponent_ranking",
        "team2_top_10_win_rate",
        "team2_upset_factor",
        "h2h_matches",
        "team1_h2h_wins",
        "team1_h2h_win_rate",
        "ranking_diff",
        "rating_diff",
        "win_rate_diff",
        "avg_score_diff",
        "recent_form_diff"
    ],
    "feature_importance": {
        "Feature": {
            "39": "win_rate_diff",
            "21": "team2_recency_weighted_win_rate",
            "40": "avg_score_diff",
            "7": "team2_win_rate",
            "26": "team2_online_win_rate",
            "9": "team2_score_diff",
            "8": "team2_avg_score",
            "6": "team2_wins",
            "19": "team2_recent_form_10",
            "5": "team2_matches",
            "18": "team2_recent_form_5",
            "41": "recent_form_diff",
            "27": "team2_lan_vs_online_diff",
            "25": "team2_lan_win_rate",
            "20": "team2_form_trajectory",
            "0": "team1_matches",
            "4": "team1_score_diff",
            "1": "team1_wins",
            "3": "team1_avg_score",
            "2": "team1_win_rate",
            "15": "team1_recent_form_10",
            "16": "team1_form_trajectory",
            "17": "team1_recency_weighted_win_rate",
            "10": "team1_ranking",
            "12": "team1_rating",
            "11": "team2_ranking",
            "24": "team1_lan_vs_online_diff",
            "23": "team1_online_win_rate",
            "22": "team1_lan_win_rate",
            "13": "team2_rating",
            "14": "team1_recent_form_5",
            "30": "team1_upset_factor",
            "28": "team1_avg_opponent_ranking",
            "29": "team1_top_10_win_rate",
            "33": "team2_upset_factor",
            "32": "team2_top_10_win_rate",
            "31": "team2_avg_opponent_ranking",
            "34": "h2h_matches",
            "37": "ranking_diff",
            "36": "team1_h2h_win_rate",
            "35": "team1_h2h_wins",
            "38": "rating_diff"
        },
        "Importance": {
            "39": 0.10483514057215185,
            "21": 0.10149694586827746,
            "40": 0.09689614634912118,
            "7": 0.09613962081539087,
            "26": 0.09396513659753766,
            "9": 0.09154287424494197,
            "8": 0.08871478218746513,
            "6": 0.081476713318547,
            "19": 0.05422469825997832,
            "5": 0.052458335917686616,
            "18": 0.03439433253711504,
            "41": 0.028874735483239024,
            "27": 0.027217991897230665,
            "25": 0.02493832792674761,
            "20": 0.02282421802456957,
            "0": 0.0,
            "4": 0.0,
            "1": 0.0,
            "3": 0.0,
            "2": 0.0,
            "15": 0.0,
            "16": 0.0,
            "17": 0.0,
            "10": 0.0,
            "12": 0.0,
            "11": 0.0,
            "24": 0.0,
            "23": 0.0,
            "22": 0.0,
            "13": 0.0,
            "14": 0.0,
            "30": 0.0,
            "28": 0.0,
            "29": 0.0,
            "33": 0.0,
            "32": 0.0,
            "31": 0.0,
            "34": 0.0,
            "37": 0.0,
            "36": 0.0,
            "35": 0.0,
            "38": 0.0
        }
    },
    "model_params": {
        "n_estimators": 300,
        "min_samples_split": 5,
        "min_samples_leaf": 1,
        "max_features": "log2",
        "max_depth": 10
    },
    "scaling_mean": [
        133.0,
        90.0,
        0.6766917293233083,
        1.3533834586466167,
        0.556390977443609,
        127.05714285714286,
        72.62857142857143,
        0.5918528642316279,
        1.265448340489205,
        0.317033778516417,
        9999.0,
        9999.0,
        1500.0,
        1500.0,
        0.8000000000000002,
        0.6000000000000001,
        0.20000000000000007,
        0.6771945118242719,
        0.4914285714285713,
        0.5685714285714285,
        -0.07714285714285714,
        0.5929981027806317,
        0.0,
        0.6870229007633589,
        -0.6870229007633589,
        0.22925199139484853,
        0.5984999543386783,
        -0.10956946772890726,
        0.0,
        0.0,
        0.0,
        0.0,
        0.0,
        0.0,
        0.0,
        0.0,
        0.0,
        0.0,
        0.0,
        0.0848388650916804,
        0.0879351181574115,
        0.30857142857142866
    ],
    "scaling_scale": [
        1.0,
        1.0,
        1.0,
        1.0,
        1.0,
        64.267718115993,
        38.554663022990184,
        0.12100308042744683,
        0.24214554140867448,
        0.4081819724249679,
        1.0,
        1.0,
        1.0,
        1.0,
        1.0,
        1.0,
        1.0,
        1.0,
        0.2309872335018027,
        0.1507532109516905,
        0.1097678440702774,
        0.12336963112002677,
        1.0,
        1.0,
        1.0,
        0.2221195940724418,
        0.12168777253880814,
        0.13477380693812305,
        1.0,
        1.0,
        1.0,
        1.0,
        1.0,
        1.0,
        1.0,
        1.0,
        1.0,
        1.0,
        1.0,
        0.1210030804274468,
        0.24214554140867448,
        0.2309872335018027
    ]
}